{
  "name": "images/jFPYqC2aOFaeQHBVh0tfl0D6otEX/avatar.png",
  "bucket": "speedy-league-335221.appspot.com",
  "metageneration": 1,
  "generation": 1699516172174,
  "contentType": "image/png",
  "storageClass": "STANDARD",
  "contentDisposition": "inline",
  "downloadTokens": [
    "ae15ae36-c53f-45ec-a908-947d89378973"
  ],
  "etag": "1g2Ch1Eizc0CKbtGUpTd3UP4CPI",
  "customMetadata": {},
  "timeCreated": "2023-11-09T07:49:32.177Z",
  "updated": "2023-11-09T07:49:32.177Z",
  "size": 1575864,
  "md5Hash": "8tem4AaiikWixPRNoRq9CA==",
  "crc32c": "714243905"
}